README.rst
setup.py
sqlash/__init__.py
sqlash/langhelpers.py
sqlash.egg-info/PKG-INFO
sqlash.egg-info/SOURCES.txt
sqlash.egg-info/dependency_links.txt
sqlash.egg-info/entry_points.txt
sqlash.egg-info/not-zip-safe
sqlash.egg-info/requires.txt
sqlash.egg-info/top_level.txt
sqlash/tests/__init__.py
sqlash/tests/test_it.py