Metadata-Version: 1.1
Name: sqlash
Version: 0.1
Summary: sqlalchemy shorthand (dict from object)
Home-page: UNKNOWN
Author: UNKNOWN
Author-email: UNKNOWN
License: UNKNOWN
Platform: UNKNOWN
Classifier: Programming Language :: Python
Classifier: Programming Language :: Python :: Implementation :: CPython
